red_config-0.1.0.dist-info/METADATA
red_config-0.1.0.dist-info/WHEEL
red_config/__init__.py
red_config/config.py
red_config/config_utils/__init__.py
red_config/config_utils/operations.py
red_config/extra/__init__.py
red_config/extra/api_config.py
red_config-0.1.0.dist-info/RECORD
